Workbook

Sheet Assumptions
A5: Assumptions
A6: Driver Switch | B6: 3
A7: Assumptions
B8: NO. Campanies | F8: 2027 | G8: 2028 | H8: 2029
C9: NO. Campanies | F9: {=INDEX(F11:F13,$B$6)} -> 3 | G9: {=INDEX(G11:G13,$B$6)} -> 5 | H9: {=INDEX(H11:H13,$B$6)} -> 10
C11: Best Case | F11: 10 | G11: 15 | H11: 20
C12: Base Case | F12: 8 | G12: 10 | H12: 15
C13: Worst Case | F13: 3 | G13: 5 | H13: 10
B16: NO. Events | F16: =F8 -> 2027 | G16: =G8 -> 2028 | H16: =H8 -> 2029
C17: Event | F17: {=INDEX(F19:F21,$B$6)} -> 12 | G17: {=INDEX(G19:G21,$B$6)} -> 20 | H17: {=INDEX(H19:H21,$B$6)} -> 40
C19: Best Case | F19: =F11*7 -> 70 | G19: =G11*7 -> 105 | H19: =H11*7 -> 140
C20: Base Case | F20: =F12*5 -> 40 | G20: =G12*5 -> 50 | H20: =H12*5 -> 75
C21: Worst Case | F21: =F13*4 -> 12 | G21: =G13*4 -> 20 | H21: =H13*4 -> 40
B23: NO. Guests | F23: =F16 -> 2027 | G23: =G16 -> 2028 | H23: =H16 -> 2029
C24: NO Guests to spicial trip | F24: {=INDEX(F53:F55,$B$6)} -> 3600 | G24: {=INDEX(G53:G55,$B$6)} -> 6000 | H24: {=INDEX(H53:H55,$B$6)} -> 12000
B26: NO. Guests In Project | F26: =F23 -> 2027 | G26: =G23 -> 2028 | H26: =H23 -> 2029
C27: Best Case | F27: 200 | G27: 200 | H27: 200 | J27: نمو عدد الضيوف
C28: Base Case | F28: 150 | G28: 150 | H28: 150
C29: Worst Case | F29: 100 | G29: 100 | H29: 100
B31: Totel Of Guests | F31: =F26 -> 2027 | G31: =G26 -> 2028 | H31: =H26 -> 2029
C32: Best Case | F32: =F27*F19 -> 14000 | G32: =G27*G19 -> 21000 | H32: =H27*H19 -> 28000
C33: Base Case | F33: =F28*F20 -> 6000 | G33: =G28*G20 -> 7500 | H33: =H28*H20 -> 11250
C34: Worst Case | F34: =F21*F29 -> 1200 | G34: =G21*G29 -> 2000 | H34: =H21*H29 -> 4000
B38: Conversion | F38: =F31 -> 2027 | G38: =G31 -> 2028 | H38: =H31 -> 2029
C39: Best Case | F39: 0.5 | G39: 0.5 | H39: 0.5
C40: Base Case | F40: 0.25 | G40: 0.25 | H40: 0.25
C41: Worst Case | F41: 0.1 | G41: 0.1 | H41: 0.1
B44: AVG Cost Of The Trip | F44: =F38 -> 2027 | G44: =G38 -> 2028 | H44: =H38 -> 2029
C45: Best Case | F45: 30 | G45: 30 | H45: 30
C46: Base Case | F46: 30 | G46: 30 | H46: 30
C47: Worst Case | F47: 30 | G47: 30 | H47: 30
F49: =F44 -> 2027 | G49: =G44 -> 2028 | H49: =H44 -> 2029
C50: Revenue Of The Trip | F50: {=INDEX(F53:F55,$B$6)} -> 3600 | G50: {=INDEX(G53:G55,$B$6)} -> 6000 | H50: {=INDEX(H53:H55,$B$6)} -> 12000
B52: Revenue Of The Trip | F52: =F49 -> 2027 | G52: =G49 -> 2028 | H52: =H49 -> 2029
C53: Best Case | F53: =F45*F39*F32 -> 210000 | G53: =G45*G39*G32 -> 315000 | H53: =H45*H39*H32 -> 420000
C54: Base Case | F54: =F46*F40*F33 -> 45000 | G54: =G46*G40*G33 -> 56250 | H54: =H46*H40*H33 -> 84375
C55: Worst Case | F55: =F47*F41*F34 -> 3600 | G55: =G47*G41*G34 -> 6000 | H55: =H47*H41*H34 -> 12000
B57: Event volume | F57: =F52 -> 2027 | G57: =G52 -> 2028 | H57: =H52 -> 2029
C58: Cars | F58: {=INDEX(F63:F65,$B$6)} -> 327600 | G58: {=INDEX(G63:G65,$B$6)} -> 546000 | H58: {=INDEX(H63:H65,$B$6)} -> 1092000
C59: Tickit | F59: {=INDEX(F68:F70,$B$6)} -> 147000 | G59: {=INDEX(G68:G70,$B$6)} -> 245000 | H59: {=INDEX(H68:H70,$B$6)} -> 490000
C60: Hotels | F60: {=INDEX(F73:F75,$B$6)} -> 384000 | G60: {=INDEX(G73:G75,$B$6)} -> 640000 | H60: {=INDEX(H73:H75,$B$6)} -> 1280000
C61: Event volume | F61: =SUM(F58:F60) -> 858600 | G61: =SUM(G58:G60) -> 1431000 | H61: =SUM(H58:H60) -> 2862000
B62: cars | F62: =F57 -> 2027 | G62: =G57 -> 2028 | H62: =H57 -> 2029
C63: Best Case | F63: =((((F27/4)*F19)*1300)*14%)*6 -> 3822000 | G63: =((((G27/4)*G19)*1300)*14%)*6 -> 5733000 | H63: =((((H27/4)*H19)*1300)*14%)*6 -> 7644000
C64: Base Case | F64: =((((F28/4)*F20)*1300)*14%)*6 -> 1638000 | G64: =((((G28/4)*G20)*1300)*14%)*6 -> 2047500 | H64: =((((H28/4)*H20)*1300)*14%)*6 -> 3071250
C65: Worst Case | F65: =((((F29/4)*F21)*1300)*14%)*6 -> 327600 | G65: =((((G29/4)*G21)*1300)*14%)*6 -> 546000 | H65: =((((H29/4)*H21)*1300)*14%)*6 -> 1092000
B67: Tickit | F67: =F62 -> 2027 | G67: =G62 -> 2028 | H67: =H62 -> 2029
C68: Best Case | F68: =((F32*70%)*3500)*5% -> 1715000 | G68: =((G32*70%)*3500)*5% -> 2572500 | H68: =((H32*70%)*3500)*5% -> 3430000
C69: Base Case | F69: =((F33*70%)*3500)*5% -> 735000 | G69: =((G33*70%)*3500)*5% -> 918750 | H69: =((H33*70%)*3500)*5% -> 1378125
C70: Worst Case | F70: =((F34*70%)*3500)*5% -> 147000 | G70: =((G34*70%)*3500)*5% -> 245000 | H70: =((H34*70%)*3500)*5% -> 490000
B72: Hotels | F72: =F67 -> 2027 | G72: =G67 -> 2028 | H72: =H67 -> 2029
C73: Best Case | F73: =(F32/1.5)*1200*4*10% -> 4480000 | G73: =(G32/1.5)*1200*4*10% -> 6720000 | H73: =(H32/1.5)*1200*4*10% -> 8960000
C74: Base Case | F74: =(F33/1.5)*1200*4*10% -> 1920000 | G74: =(G33/1.5)*1200*4*10% -> 2400000 | H74: =(H33/1.5)*1200*4*10% -> 3600000
C75: Worst Case | F75: =(F34/1.5)*1200*4*10% -> 384000 | G75: =(G34/1.5)*1200*4*10% -> 640000 | H75: =(H34/1.5)*1200*4*10% -> 1280000
A78: Cost
C79: Guest APP | F79: {=INDEX(F86:F88,$B$6)} -> 40000
C80: Driver APP | F80: {=INDEX(F92:F94,$B$6)} -> 30000
C81: Dashboard | F81: {=INDEX(F97:F99,$B$6)} -> 30000
C82: Backend + Marketplace | F82: {=INDEX(F102:F104,$B$6)} -> 40000
B85: Guest APP | F85: 2027
C86: Best Case | F86: 70000
C87: Base Case | F87: 55000
C88: Worst Case | F88: 40000
B91: Driver APP | F91: 2027
C92: Best Case | F92: 50000
C93: Base Case | F93: 40000
C94: Worst Case | F94: 30000
B96: Dashboard | F96: 2027
C97: Best Case | F97: 80000
C98: Base Case | F98: 55000
C99: Worst Case | F99: 30000
B101: Backend + Marketplace | F101: 2027
C102: Best Case | F102: 100000
C103: Base Case | F103: 70000
C104: Worst Case | F104: 40000
A107: SALARES
F108: 2027 | G108: 2028 | H108: 2029
B109: Founder / CEO | F109: =20000*12 -> 240000 | G109: =20000*12 -> 240000 | H109: =20000*12 -> 240000 | J109: الرئيس التنفيذي
B110: Full Stack Developer | F110: =20000*12 -> 240000 | G110: =20000*12 -> 240000 | H110: =20000*12 -> 240000 | J110: مطور كامل المستوى
B111: Mobile Developer | F111: =20000*12 -> 240000 | G111: =20000*12 -> 240000 | H111: =20000*12 -> 240000 | J111: مطور تطبيقات الجوال
B112: UI/UX Designer | F112: =10000*6 -> 60000 | G112: 0 | H112: 0 | J112: مصمم واجهات المستخدم
B113: QA Engineer | F113: =8000*6 -> 48000 | G113: 0 | H113: 0 | J113: مهندس ضمان جودة
B114: DevOps Engineer | F114: =5000*6 -> 30000 | G114: 0 | H114: 0 | J114: مهندس DevOps
B115: Product / Operations Lead | F115: =18000*12 -> 216000 | G115: =18000*12 -> 216000 | H115: =18000*12 -> 216000 | J115: مدير العمليات والمنتج
B116: Customer Support | F116: =7000*3 -> 21000 | G116: =7000*12 -> 84000 | H116: =7000*12 -> 84000 | J116: مسؤول دعم العملاء
B117: Business Development Manager | F117: =15000*4 -> 60000 | G117: =15000*12 -> 180000 | H117: =15000*12 -> 180000
B118: Digital Marketer | F118: =10000*4 -> 40000 | G118: =10000*12 -> 120000 | H118: =10000*12 -> 120000
B119: Sales Manager | F119: 0 | G119: =16000*12 -> 192000 | H119: =16000*12 -> 192000
B120: Accountant | F120: =7000*12 -> 84000 | G120: =7000*12 -> 84000 | H120: =7000*12 -> 84000
B121: Compliance / Cybersecurity Officer | F121: =7000*6 -> 42000 | G121: =7000*12 -> 84000 | H121: =7000*12 -> 84000
B122: AI / ML Engineer | F122: =25000*12 -> 300000 | G122: =25000*12 -> 300000 | H122: =25000*12 -> 300000
B125: 2027 | C125: 2028 | D125: 2029
A126: NO. Geust | B126: {=INDEX(F32:F34,$B$6)} -> 1200 | C126: {=INDEX(G32:G34,$B$6)} -> 2000 | D126: {=INDEX(H32:H34,$B$6)} -> 4000 | E126: {=INDEX(I32:I34,$B$6)} -> 0 | F126: {=INDEX(J32:J34,$B$6)} -> 0
A128: Direct Cost | F128: 2027 | G128: 2028 | H128: 2029
B130: SMS / OTP | F130: =B126*0.5*5 -> 3000 | G130: =C126*0.5*5 -> 5000 | H130: =D126*0.5*5 -> 10000
B132: Email API | F132: =CEILING((B126*10)/50000,1)*188 -> 188 | G132: =CEILING((C126*10)/50000,1)*188 -> 188 | H132: =CEILING((D126*10)/50000,1)*188 -> 188
B134: Maps API | F134: =B126*4 -> 4800 | G134: =C126*4 -> 8000 | H134: =D126*4 -> 16000
B136: AI API Usage | F136: =B126*3 -> 3600 | G136: =C126*3 -> 6000 | H136: =D126*3 -> 12000
B138: Storage | F138: =200*12 -> 2400 | G138: =300*12 -> 3600 | H138: =500*12 -> 6000
B140: Push Notifications API | F140: =0.5*B126 -> 600 | G140: =0.5*C126 -> 1000 | H140: =0.5*D126 -> 2000 | M140: و واجهة برمجية تسمح لتطبيقك بإرسال إشعارات للمستخدم حتى لو كان التطبيق مغلق أو غير نشط
...

Sheet Income statement
A1: Income Statemaent
C2: Revenue
D3: =Assumptions!C58 -> Cars | H3: =Assumptions!F58 -> 327600 | I3: =Assumptions!G58 -> 546000 | J3: =Assumptions!H58 -> 1092000
D4: =Assumptions!C59 -> Tickit | H4: =Assumptions!F59 -> 147000 | I4: =Assumptions!G59 -> 245000 | J4: =Assumptions!H59 -> 490000
D5: =Assumptions!C60 -> Hotels | H5: =Assumptions!F60 -> 384000 | I5: =Assumptions!G60 -> 640000 | J5: =Assumptions!H60 -> 1280000
C6: Total Revenue | H6: =SUM(H3:H5) -> 858600 | I6: =SUM(I3:I5) -> 1431000 | J6: =SUM(J3:J5) -> 2862000
C7: Cost Of Revenue
D8: SMS / OTP | H8: =Assumptions!F130 -> 3000 | I8: =Assumptions!G130 -> 5000 | J8: =Assumptions!H130 -> 10000
D9: Email API | H9: =Assumptions!F132 -> 188 | I9: =Assumptions!G132 -> 188 | J9: =Assumptions!H132 -> 188
D10: Maps API | H10: =Assumptions!F134 -> 4800 | I10: =Assumptions!G134 -> 8000 | J10: =Assumptions!H134 -> 16000
D11: AI API Usage | H11: =Assumptions!F136 -> 3600 | I11: =Assumptions!G136 -> 6000 | J11: =Assumptions!H136 -> 12000
D12: Storage | H12: =Assumptions!F138 -> 2400 | I12: =Assumptions!G138 -> 3600 | J12: =Assumptions!H138 -> 6000
D13: Push Notifications API | H13: =Assumptions!F140 -> 600 | I13: =Assumptions!G140 -> 1000 | J13: =Assumptions!H140 -> 2000
D14: CDN | H14: =Assumptions!F142 -> 2400 | I14: =Assumptions!G142 -> 3600 | J14: =Assumptions!H142 -> 6000
C15: Total Cost | H15: =SUM(H8:H14) -> 16988 | I15: =SUM(I8:I14) -> 27388 | J15: =SUM(J8:J14) -> 52188
C16: Grose Profit | H16: =H6-H15 -> 841612 | I16: =I6-I15 -> 1403612 | J16: =J6-J15 -> 2809812
C17: Operating Expenses
D18: Founder / CEO | H18: =Assumptions!F109 -> 240000 | I18: =Assumptions!G109 -> 240000 | J18: =Assumptions!H109 -> 240000
D19: Full Stack Developer | H19: =Assumptions!F110 -> 240000 | I19: =Assumptions!G110 -> 240000 | J19: =Assumptions!H110 -> 240000
D20: Mobile Developer | H20: =Assumptions!F111 -> 240000 | I20: =Assumptions!G111 -> 240000 | J20: =Assumptions!H111 -> 240000
D21: UI/UX Designer | H21: =Assumptions!F112 -> 60000 | I21: =Assumptions!G112 -> 0 | J21: =Assumptions!H112 -> 0
D22: QA Engineer | H22: =Assumptions!F113 -> 48000 | I22: =Assumptions!G113 -> 0 | J22: =Assumptions!H113 -> 0
D23: DevOps Engineer | H23: =Assumptions!F114 -> 30000 | I23: =Assumptions!G114 -> 0 | J23: =Assumptions!H114 -> 0
D24: Product / Operations Lead | H24: =Assumptions!F115 -> 216000 | I24: =Assumptions!G115 -> 216000 | J24: =Assumptions!H115 -> 216000
D25: Customer Support | H25: =Assumptions!F116 -> 21000 | I25: =Assumptions!G116 -> 84000 | J25: =Assumptions!H116 -> 84000
D26: Business Development Manager | H26: =Assumptions!F117 -> 60000 | I26: =Assumptions!G117 -> 180000 | J26: =Assumptions!H117 -> 180000
D27: Digital Marketer | H27: =Assumptions!F118 -> 40000 | I27: =Assumptions!G118 -> 120000 | J27: =Assumptions!H118 -> 120000
D28: Sales Manager | H28: =Assumptions!F119 -> 0 | I28: =Assumptions!G119 -> 192000 | J28: =Assumptions!H119 -> 192000
D29: Accountant | H29: =Assumptions!F120 -> 84000 | I29: =Assumptions!G120 -> 84000 | J29: =Assumptions!H120 -> 84000
... D31: AI / ML Engineer | H31: =Assumptions!F122 -> 300000 | I31: =Assumptions!G122 -> 300000 | J31: =Assumptions!H122 -> 300000
D32: Office Rent | H32: =Assumptions!F144 -> 60000 | I32: =Assumptions!G144 -> 60000 | J32: =Assumptions!H144 -> 60000
D33: Internet | H33: =Assumptions!F145 -> 3600 | I33: =Assumptions!G145 -> 3600 | J33: =Assumptions!H145 -> 3600
D34: Utilities | H34: =Assumptions!F146 -> 6000 | I34: =Assumptions!G146 -> 6000 | J34: =Assumptions!H146 -> 6000
D35: Furniture | H35: =Assumptions!F147 -> 50000 | I35: =Assumptions!G147 -> 2500 | J35: =Assumptions!H147 -> 2500
D36: Laptops | H36: =Assumptions!F148 -> 42000 | I36: =Assumptions!G148 -> 1000 | J36: =Assumptions!H148 -> 5000
D37: Office Supplies | H37: =Assumptions!F149 -> 1800 | I37: =Assumptions!G149 -> 1800 | J37: =Assumptions!H149 -> 1800
D38: Software Tools | H38: =Assumptions!F150 -> 4800 | I38: =Assumptions!G150 -> 4800 | J38: =Assumptions!H150 -> 4800
D39: Maintenance | H39: =Assumptions!F151 -> 24000 | I39: =Assumptions!G151 -> 24000 | J39: =Assumptions!H151 -> 24000
D40: Hosting / Cloud | H40: =Assumptions!F152 -> 36000 | I40: =Assumptions!G152 -> 48000 | J40: =Assumptions!H152 -> 72000
D41: DevOps Part-time | H41: =Assumptions!F153 -> 3000 | I41: =Assumptions!G153 -> 3000 | J41: =Assumptions!H153 -> 3000
D42: Security Audit | H42: =Assumptions!F154 -> 10000 | I42: =Assumptions!G154 -> 10000 | J42: =Assumptions!H154 -> 10000
D43: Monitoring (Sentry / Datadog) | H43: =Assumptions!F155 -> 8000 | I43: =Assumptions!G155 -> 8000 | J43: =Assumptions!H155 -> 8000
... D46: Product Launch Event | H46: =Assumptions!F158 -> 250000 | I46: =Assumptions!G158 -> 0 | J46: =Assumptions!H158 -> 0
D47: Legal & Compliance | H47: =Assumptions!F160 -> 60000 | I47: =Assumptions!G160 -> 60000 | J47: =Assumptions!H160 -> 60000
D48: Travel & Meetings | H48: =Assumptions!F161 -> 24000 | I48: =Assumptions!G161 -> 24000 | J48: =Assumptions!H161 -> 24000
D49: Civil Liability Insurance | H49: =Assumptions!F163 -> 4000 | I49: =Assumptions!G163 -> 4000 | J49: =Assumptions!H163 -> 4000
C50: Total Operating Expenses | H50: =SUM(H18:H49) -> 2274200 | I50: =SUM(I18:I49) -> 2306700 | J50: =SUM(J18:J49) -> 2335600
C51: EBITDA | H51: =H16-H50 -> -1432588 | I51: =I16-I50 -> -903088 | J51: =J16-J50 -> 474212
D53: Depreciation | H53: =Assumptions!F169 -> 30666.667 | I53: =Assumptions!G169 -> 30666.667 | J53: =Assumptions!H169 -> 30666.667
C54: NET Profit | H54: =H51-H53 -> -1463254.7 | I54: =I51-I53 -> -933754.67 | J54: =J51-J53 -> 443545.33

Sheet clarifications
A1: ما في تكلفة صيانة سنوية
B2: Payment Gateway Fees هل بنحتاجه
A3: ما في تكلفة سيرفرات
A5: ما في تكلفة AI
A7: ما في تكلفة DevOps / Security
A9: ما في تكلفة Hosting
A11: ما في تكلفة Integrations (خرائط – SMS – OTP – Email)
A16: SMS / OTP | B16: رسائل التحقق (OTP) و رسائل تحديثات الضيوف و رسائل للسائقين و رسائل تأكيد الحجوزات
A18: Email API | B18: إرسال الإيميلات للضيوف تأكيد الدعوات إرسال الفواتير إشعارات النظام | J18: كل اربعه يوف سياره
J19: كل ضيف VIP سياره
A20: Maps API (خرائط – تتبع – حساب مسافات) | B20: في الفعاليات الكبيرة (تتبع مستمر): 3,000 – 10,000 ريال | J20: كل 70 ضيف سيارة قولف
J21: كل 150 ضيف حاويه
A22: AI API Usage (مثل OpenAI) | B22: تشغيل المرشد الذكي "سعود" الردود الذكية الترجمة تحليل الطلبات تلخيص البيانات | J22: كل 200 ضيف سيارة شحن
J23: كل 300 ضيف معدات ثقيله
A24: Payment Gateway Fees | B24: رسوم بوابة الدفع عند: شراء تذاكر دفع خدمات حجوزات Marketplace
A26: Storage للصور والفواتير | J26: اسئله
J27: كم نسبه وكالات السفر في التذكره
A28: CDN للاستخدام العالي | B28: سريع تحميل الصور تسريع تحميل الملفات تحسين أداء التطبيقات Cloudflare / AWS CloudFront
J29: نصيحه
J30: Developer واحد
J31: Operations قوي جدًا
J32: Sales ذكي
A34: A) الرواتب (Salaries) | J34: ❌ لا تبني فريق كبير تقني من البداية
C35: كلما زاد عدد الضيوف زادت المصاريف
A36: Full Stack Developer | C36: المشكلة الثانية — تكاليف التقنية ثابتة وغير مرتبطة بالحجم تكاليف الخرائط والرسائل القصيرة والذكاء الاصطناعي جميعها ثابتة سنوياً بصرف النظر عن عدد الضيوف. هذا خطأ كبير، لأن هذه التكاليف تزداد مع كل ضيف وكل فعالية. عند 11,250 ضيف في السيناريو المتوسط لسنة 2029، تكاليف الخرائط وحدها ستكون أضعاف الرقم المذكور.
C37: اقتراحي أن تضع باقتين، الأولى مجانية بعمولة 18% وبدون أولوية ظهور، والثانية باشتراك بين 500 و 1,000 ريال شهرياً بعمولة 10% وبأولوية الظهور. هذا الرقم يغطي جزءاً من تكاليفك التشغيلية المباشرة ويعطي المورد حافزاً واضحاً للاشتراك.
A38: UI/UX Designer
A40: Product Architect (دمج PM + Ops Lead)
A42: Business Development
A44: Customer Support
A46: Accountant (Outsource)
A48: B) البنية التحتية التقنية (Infrastructure)
A50: Hosting / Servers (AWS / Azure / GCP)
A52: Database
A54: Backups
A56: Monitoring (Sentry / Datadog)
A58: Analytics (Mixpanel / Amplitude)
A60: DevOps (Part-time)
... A168: اجتماعات حكومية
